beesly/__init__.py
beesly/classes.py
beesly/exceptions.py
beesly/functions.py
beesly/helpers.py
beesly-0.0.2.dist-info/LICENSE
beesly-0.0.2.dist-info/METADATA
beesly-0.0.2.dist-info/WHEEL
beesly-0.0.2.dist-info/top_level.txt
beesly-0.0.2.dist-info/RECORD
