Metadata-Version: 2.1
Name: beesly
Version: 0.0.2
Summary: Web Scraping for Humans
Home-page: https://github.com/Chicken1Geek/beesly
Author: Sachin Sankar
Author-email: mail.sachinsankar@gmail.com
Classifier: Development Status :: 2 - Pre-Alpha
License-File: LICENSE
Requires-Dist: beautifulsoup4
Requires-Dist: requests
Requires-Dist: user-agent
